solveit/__init__.py
Solveit-0.1.2.dist-info/LICENSE
Solveit-0.1.2.dist-info/METADATA
Solveit-0.1.2.dist-info/WHEEL
Solveit-0.1.2.dist-info/top_level.txt
Solveit-0.1.2.dist-info/RECORD
