Metadata-Version: 2.1
Name: Solveit
Version: 0.1.2
Summary: A comprehensive toolkit for data processing and problem-solving
Home-page: https://github.com/KashyapSinh-Gohil/Solveit
Author: Kashyapsinh Gohil
Author-email: k.agohil000@gmail.com
Project-URL: Bug Tracker, https://github.com/KashyapSinh-Gohil/Solveit/issues
Classifier: Development Status :: 4 - Beta
Classifier: Intended Audience :: Developers
Classifier: Intended Audience :: Science/Research
Classifier: License :: OSI Approved :: MIT License
Classifier: Operating System :: OS Independent
Classifier: Programming Language :: Python :: 3
Classifier: Programming Language :: Python :: 3.7
Classifier: Programming Language :: Python :: 3.8
Classifier: Programming Language :: Python :: 3.9
Classifier: Programming Language :: Python :: 3.10
Classifier: Programming Language :: Python :: 3.11
Classifier: Programming Language :: Python :: 3.12
Classifier: Programming Language :: Python :: 3.13
Classifier: Topic :: Scientific/Engineering
Classifier: Topic :: Software Development :: Libraries :: Python Modules
Requires-Python: >=3.7
License-File: LICENSE
Requires-Dist: numpy>=1.20.0
Requires-Dist: pandas>=1.3.0
Requires-Dist: matplotlib>=3.4.0
Requires-Dist: scipy>=1.7.0
Requires-Dist: networkx>=2.6.0
Requires-Dist: pytest>=7.0.0
Requires-Dist: pytest-cov>=4.0.0
Requires-Dist: openpyxl>=3.0.0
Requires-Dist: xlrd>=2.0.0
Provides-Extra: dev
Requires-Dist: pytest>=7.0.0; extra == "dev"
Requires-Dist: pytest-cov>=4.0.0; extra == "dev"
Requires-Dist: black>=22.0.0; extra == "dev"
Requires-Dist: isort>=5.0.0; extra == "dev"
Requires-Dist: mypy>=0.900; extra == "dev"
Requires-Dist: twine>=3.4.0; extra == "dev"
